iris/__init__.py
iris/_version.py
iris/callbacks/__init__.py
iris/callbacks/callback_interface.py
iris/callbacks/pipeline_trace.py
iris/io/__init__.py
iris/io/class_configs.py
iris/io/dataclasses.py
iris/io/errors.py
iris/io/validators.py
iris/nodes/__init__.py
iris/nodes/aggregation/__init__.py
iris/nodes/aggregation/noise_mask_union.py
iris/nodes/binarization/__init__.py
iris/nodes/binarization/multilabel_binarization.py
iris/nodes/binarization/specular_reflection_detection.py
iris/nodes/encoder/__init__.py
iris/nodes/encoder/iris_encoder.py
iris/nodes/eye_properties_estimation/__init__.py
iris/nodes/eye_properties_estimation/bisectors_method.py
iris/nodes/eye_properties_estimation/eccentricity_offgaze_estimation.py
iris/nodes/eye_properties_estimation/iris_bbox_calculator.py
iris/nodes/eye_properties_estimation/moment_of_area.py
iris/nodes/eye_properties_estimation/occlusion_calculator.py
iris/nodes/eye_properties_estimation/pupil_iris_property_calculator.py
iris/nodes/eye_properties_estimation/sharpness_estimation.py
iris/nodes/geometry_estimation/__init__.py
iris/nodes/geometry_estimation/fusion_extrapolation.py
iris/nodes/geometry_estimation/linear_extrapolation.py
iris/nodes/geometry_estimation/lsq_ellipse_fit_with_refinement.py
iris/nodes/geometry_refinement/__init__.py
iris/nodes/geometry_refinement/contour_interpolation.py
iris/nodes/geometry_refinement/contour_points_filter.py
iris/nodes/geometry_refinement/smoothing.py
iris/nodes/iris_response/__init__.py
iris/nodes/iris_response/conv_filter_bank.py
iris/nodes/iris_response/image_filters/__init__.py
iris/nodes/iris_response/image_filters/gabor_filters.py
iris/nodes/iris_response/image_filters/image_filter_interface.py
iris/nodes/iris_response/probe_schemas/__init__.py
iris/nodes/iris_response/probe_schemas/probe_schema_interface.py
iris/nodes/iris_response/probe_schemas/regular_probe_schema.py
iris/nodes/iris_response_refinement/__init__.py
iris/nodes/iris_response_refinement/fragile_bits_refinement.py
open_iris-1.10.0.dist-info/licenses/LICENSE
open_iris-1.10.0.dist-info/METADATA
open_iris-1.10.0.dist-info/WHEEL
open_iris-1.10.0.dist-info/top_level.txt
open_iris-1.10.0.dist-info/RECORD
