Metadata-Version: 2.4
Name: open-iris
Version: 1.10.0
Summary: IRIS: Iris Recognition Inference System of the Worldcoin project.
Home-page: https://github.com/worldcoin/open-iris
Author: Worldcoin AI
Author-email: ai@worldcoin.org
License: MIT
Keywords: biometrics,iris recognition
Classifier: License :: OSI Approved :: MIT License
Classifier: Programming Language :: Python :: 3
Classifier: Programming Language :: Python :: 3.8
Classifier: Programming Language :: Python :: 3.9
Classifier: Programming Language :: Python :: 3.10
Classifier: Operating System :: OS Independent
Requires-Python: >=3.8
License-File: LICENSE
Requires-Dist: huggingface-hub==0.19.4
Requires-Dist: matplotlib==3.7.4
Requires-Dist: numpy==1.24.4
Requires-Dist: pydantic==1.10.13
Requires-Dist: pyyaml==6.0.1
Requires-Dist: onnx==1.15.0
Requires-Dist: onnxruntime==1.16.3
Requires-Dist: opencv-python==4.7.0.68
Dynamic: author
Dynamic: author-email
Dynamic: classifier
Dynamic: description
Dynamic: description-content-type
Dynamic: home-page
Dynamic: keywords
Dynamic: license
Dynamic: license-file
Dynamic: requires-dist
Dynamic: requires-python
Dynamic: summary
